aspose_total_java/__init__.py
aspose_total_java-25.9.0.dist-info/licenses/license.txt
aspose_total_java-25.9.0.dist-info/METADATA
aspose_total_java-25.9.0.dist-info/WHEEL
aspose_total_java-25.9.0.dist-info/top_level.txt
aspose_total_java-25.9.0.dist-info/RECORD
