Metadata-Version: 2.4
Name: aspose-total-java
Version: 25.9.0
Summary: Meta-package for Aspose.Total for Python via Java (aggregate dependencies).
Author-email: Aspose <total@aspose.com>
License-Expression: LicenseRef-Proprietary
Project-URL: Homepage, https://products.aspose.com/total/python-java/
Project-URL: Docs, https://docs.aspose.com/total/python-java/
Project-URL: Releases, https://releases.aspose.com/total/python-java/
Project-URL: ReleaseNotes, https://releases.aspose.com/total/python-java/release-notes/
Project-URL: FreeSupport, https://forum.aspose.com/
Keywords: Aspose,Total,Java bridge,file formats,conversion,PDF,Excel,BarCode
Classifier: Development Status :: 5 - Production/Stable
Classifier: Intended Audience :: Developers
Classifier: Programming Language :: Python :: 3
Classifier: Programming Language :: Python :: 3 :: Only
Classifier: Programming Language :: Python :: 3.8
Classifier: Programming Language :: Python :: 3.9
Classifier: Programming Language :: Python :: 3.10
Classifier: Programming Language :: Python :: 3.11
Classifier: Programming Language :: Python :: 3.12
Classifier: Programming Language :: Python :: 3.13
Classifier: Topic :: Software Development :: Libraries
Classifier: Operating System :: OS Independent
Requires-Python: <3.14,>=3.8
License-File: license.txt
Requires-Dist: aspose-cells==25.9.0
Requires-Dist: aspose-diagram==25.9.0
Requires-Dist: aspose-ocr-python-java==25.2.0
Requires-Dist: aspose-pdf-for-python-via-java==24.9
Requires-Dist: aspose-barcode-for-python-via-java==25.9.0
Requires-Dist: JPype1==1.4.1
Dynamic: license-file
